
[
    {
        "name": "Authentic",
        "img": "./Shoes Authentic.webp",
        "price": 60.00,
        "id": "s1"
    },
    {
        "name": "Canvas Old Skool",
        "img": "./Shoes Canvas Old Skool.webp",
        "price": 70.00,
        "id": "s2"
    },
    {
        "name": "Checkerboard Slip-On",
        "img": "./Shoes Checkerboard Slip On.webp",
        "price": 65.00,
        "id": "s3"
    },
    {
        "name": "Era 59",
        "img": "./Shoes Era 59.webp",
        "price": 65.00,
        "id": "s4"
    },
    {
        "name": "Era",
        "img": "./Shoes Era.webp",
        "price": 70.00,
        "id": "s5"
    },
    {
        "name": "Old Skool",
        "img": "./Shoes Old Skool.webp",
        "price": 70.00,
        "id": "s6"
    },
    {
        "name": "Sk8-Hi",
        "img": "./Shoes Sk8-Hi.webp",
        "price": 65.00,
        "id": "s7"
    },
    {
        "name": "UltraRange EXO",
        "img": "./Shoes UltraRange EXO.webp",
        "price": 100.00,
        "id": "s8"
    }
 ]
